moclo/__init__.py
moclo/_impl.py
moclo/_utils.py
moclo/errors.py
moclo/record.py
moclo/regex.py
moclo/core/__init__.py
moclo/core/_assembly.py
moclo/core/_structured.py
moclo/core/_utils.py
moclo/core/modules.py
moclo/core/parts.py
moclo/core/vectors.py
moclo/kits/__init__.py
moclo/registry/__init__.py
moclo/registry/_utils.py
moclo/registry/base.py
moclo/registry/elabftw.py
moclo-0.4.7.dist-info/COPYING
moclo-0.4.7.dist-info/METADATA
moclo-0.4.7.dist-info/WHEEL
moclo-0.4.7.dist-info/top_level.txt
moclo-0.4.7.dist-info/zip-safe
moclo-0.4.7.dist-info/RECORD
