Metadata-Version: 2.1
Name: moclo
Version: 0.4.7
Summary: A Python implementation of the MoClo system logic.
Home-page: https://github.com/althonos/moclo/
Author: Martin Larralde
Author-email: martin.larralde@ens-paris-saclay.fr
License: MIT
Project-URL: Bug Reports, https://github.com/althonos/moclo/issues
Project-URL: Changelog, https://moclo.readthedocs.io/en/latest/changes/moclo.html
Project-URL: Documentation, https://moclo.readthedocs.io/en/latest/
Project-URL: Addgene Guide, https://www.addgene.org/cloning/moclo/
Keywords: bioinformatics,synthetic biology,modular cloning,moclo
Platform: any
Classifier: Development Status :: 3 - Alpha
Classifier: Intended Audience :: Science/Research
Classifier: License :: OSI Approved :: MIT License
Classifier: Operating System :: OS Independent
Classifier: Programming Language :: Python
Classifier: Programming Language :: Python :: 3.6
Classifier: Programming Language :: Python :: 3.7
Classifier: Programming Language :: Python :: 3.8
Classifier: Programming Language :: Python :: 3.9
Classifier: Topic :: Scientific/Engineering :: Bio-Informatics
Requires-Python: !=3.0.*,!=3.1.*,!=3.2.*,!=3.3.*,!=3.5.1,>=2.7
License-File: COPYING
Requires-Dist: biopython (~=1.78)
Requires-Dist: property-cached (~=1.4)
Requires-Dist: fs (~=2.1)
Requires-Dist: six (~=1.10)
Requires-Dist: bz2file (~=0.98) ; python_version < "3"
Requires-Dist: typing (~=3.6) ; python_version < "3.6"
